redant/__init__.py
redant-0.0.1.dist-info/LICENSE.txt
redant-0.0.1.dist-info/METADATA
redant-0.0.1.dist-info/WHEEL
redant-0.0.1.dist-info/top_level.txt
redant-0.0.1.dist-info/RECORD
